<?xml version="1.0" encoding="utf-8"?>
<!DOCTYPE hibernate-mapping PUBLIC "-//Hibernate/Hibernate Mapping DTD 3.0//EN"
"http://www.hibernate.org/dtd/hibernate-mapping-3.0.dtd">
<!-- 
    Mapping file autogenerated by MyEclipse Persistence Tools
-->
<hibernate-mapping>
    <class name="com.pds.pojo.Friend" table="friend" catalog="bbs">
        <id name="id" type="java.lang.Integer">
            <column name="id" />
            <generator class="native"></generator>
        </id>
        <many-to-one name="userByUserId" class="com.pds.pojo.User" fetch="select">
            <column name="user_id" not-null="true" />
        </many-to-one>
        <many-to-one name="userByFriendId" class="com.pds.pojo.User" fetch="select">
            <column name="friend_id" not-null="true" unique="true"/>
        </many-to-one>
        <property name="userUname" type="java.lang.String">
            <column name="user_uname" length="20" />
        </property>
        <property name="friendUname" type="java.lang.String">
            <column name="friend_uname" length="20" />
        </property>
        <property name="addTime" type="java.sql.Timestamp">
            <column name="add_time" length="19" />
        </property>
    </class>
</hibernate-mapping>
